nftscan/__init__.py
nftscan/nftscan_api.py
nftscan/utils.py
nftscan_api-0.1.4.dist-info/LICENSE
nftscan_api-0.1.4.dist-info/METADATA
nftscan_api-0.1.4.dist-info/WHEEL
nftscan_api-0.1.4.dist-info/top_level.txt
nftscan_api-0.1.4.dist-info/RECORD
