Metadata-Version: 2.1
Name: nftscan-api
Version: 0.1.4
Summary: Python 3 wrapper for the NFTScan API
Home-page: https://github.com/nftscan2022/nftscan-api-python-sdk
Author: Alex Ausch
Author-email: alex@ausch.name
Maintainer: Alex Ausch
Maintainer-email: alex@ausch.name
License: MIT license
Project-URL: Source, https://github.com/nftscan2022/nftscan-api-python-sdk
Keywords: nft,blockchain,nftscan
Platform: UNKNOWN
Classifier: Development Status :: 3 - Alpha
Classifier: Intended Audience :: Developers
Classifier: Environment :: Web Environment
Classifier: License :: OSI Approved :: MIT License
Classifier: Natural Language :: English
Classifier: Programming Language :: Python
Classifier: Programming Language :: Python :: 3
Classifier: Programming Language :: Python :: 3.9
Classifier: Topic :: Software Development :: Libraries
Classifier: Topic :: Software Development :: Libraries :: Python Modules
Classifier: Topic :: Utilities
Requires-Python: >=3.9
License-File: LICENSE
Requires-Dist: requests (>=2.27.1)
Requires-Dist: parameters-validation (==1.2.0)
